{
  "isil": "DE-467",
  "path": "/data/pubhub/export/alma/prod/",
  "postprocess": true,
  "alma": {},
  "input": {
    "queue": {
      "path": "${path}",
      "pattern": "baseline.xml.bgzf"
    }
  },
  "output": {
    "elasticsearch": {
      "index": {
        "type": "titel",
        "name": "${isil}-introx-metafix-",
        "timewindow": "yyyyMMdd",
        "settings": "classpath:/elasticsearch/hbztitle-settings.json",
        "mapping": "classpath:/elasticsearch/hbztitle-mapping.json",
        "idKey": "RecordIdentifier.identifierForTheIndex"
      }
    }
  }
}
